Crypto/__init__.pyi
Crypto/__init__.py
Crypto/py.typed
Crypto/PublicKey/_edwards.py
Crypto/PublicKey/ElGamal.pyi
Crypto/PublicKey/_openssh.py
Crypto/PublicKey/DSA.pyi
Crypto/PublicKey/_montgomery.py
Crypto/PublicKey/__init__.pyi
Crypto/PublicKey/_openssh.pyi
Crypto/PublicKey/_point.pyi
Crypto/PublicKey/RSA.py
Crypto/PublicKey/_curve448.pypy39-pp73-darwin.so
Crypto/PublicKey/__init__.py
Crypto/PublicKey/ECC.py
Crypto/PublicKey/_ed25519.pypy39-pp73-darwin.so
Crypto/PublicKey/_ed448.pypy39-pp73-darwin.so
Crypto/PublicKey/RSA.pyi
Crypto/PublicKey/DSA.py
Crypto/PublicKey/_curve25519.pypy39-pp73-darwin.so
Crypto/PublicKey/ECC.pyi
Crypto/PublicKey/ElGamal.py
Crypto/PublicKey/_curve.py
Crypto/PublicKey/_point.py
Crypto/PublicKey/_nist_ecc.py
Crypto/PublicKey/_ec_ws.pypy39-pp73-darwin.so
Crypto/Util/py3compat.py
Crypto/Util/RFC1751.pyi
Crypto/Util/_raw_api.pyi
Crypto/Util/py3compat.pyi
Crypto/Util/number.py
Crypto/Util/__init__.py
Crypto/Util/_file_system.pyi
Crypto/Util/_raw_api.py
Crypto/Util/_strxor.pypy39-pp73-darwin.so
Crypto/Util/number.pyi
Crypto/Util/_cpu_features.py
Crypto/Util/asn1.pyi
Crypto/Util/RFC1751.py
Crypto/Util/_file_system.py
Crypto/Util/Padding.pyi
Crypto/Util/_cpuid_c.pypy39-pp73-darwin.so
Crypto/Util/Counter.pyi
Crypto/Util/_cpu_features.pyi
Crypto/Util/Padding.py
Crypto/Util/Counter.py
Crypto/Util/strxor.py
Crypto/Util/strxor.pyi
Crypto/Util/asn1.py
Crypto/Signature/PKCS1_PSS.py
Crypto/Signature/DSS.pyi
Crypto/Signature/pkcs1_15.pyi
Crypto/Signature/eddsa.pyi
Crypto/Signature/PKCS1_v1_5.py
Crypto/Signature/__init__.py
Crypto/Signature/PKCS1_v1_5.pyi
Crypto/Signature/pss.pyi
Crypto/Signature/pkcs1_15.py
Crypto/Signature/PKCS1_PSS.pyi
Crypto/Signature/pss.py
Crypto/Signature/eddsa.py
Crypto/Signature/DSS.py
Crypto/Hash/SHA1.pyi
Crypto/Hash/MD2.py
Crypto/Hash/RIPEMD.pyi
Crypto/Hash/SHA.pyi
Crypto/Hash/_MD4.pypy39-pp73-darwin.so
Crypto/Hash/keccak.py
Crypto/Hash/BLAKE2s.pyi
pycryptodome-3.23.0.dist-info/RECORD
pycryptodome-3.23.0.dist-info/WHEEL
pycryptodome-3.23.0.dist-info/top_level.txt
pycryptodome-3.23.0.dist-info/METADATA
pycryptodome-3.23.0.dist-info/licenses/LICENSE.rst
pycryptodome-3.23.0.dist-info/licenses/AUTHORS.rst
