Metadata-Version: 2.4
Name: pycryptodome
Version: 3.23.0
Summary: Cryptographic library for Python
Home-page: https://www.pycryptodome.org
Author: Helder Eijs
Author-email: helderijs@gmail.com
License: BSD, Public Domain
Project-URL: Source, https://github.com/Legrandin/pycryptodome/
Project-URL: Changelog, https://www.pycryptodome.org/src/changelog
Platform: Posix; MacOS X; Windows
Classifier: Development Status :: 5 - Production/Stable
Classifier: License :: OSI Approved :: BSD License
Classifier: License :: Public Domain
Classifier: Intended Audience :: Developers
Classifier: Operating System :: Unix
Classifier: Operating System :: Microsoft :: Windows
Classifier: Operating System :: MacOS :: MacOS X
Classifier: Topic :: Security :: Cryptography
Classifier: Programming Language :: Python :: 2
Classifier: Programming Language :: Python :: 2.7
Classifier: Programming Language :: Python :: 3
Classifier: Programming Language :: Python :: 3.7
Classifier: Programming Language :: Python :: 3.8
Classifier: Programming Language :: Python :: 3.9
Classifier: Programming Language :: Python :: 3.10
Classifier: Programming Language :: Python :: 3.11
Classifier: Programming Language :: Python :: 3.12
Classifier: Programming Language :: Python :: 3.13
Requires-Python: >=2.7, !=3.0.*, !=3.1.*, !=3.2.*, !=3.3.*, !=3.4.*, !=3.5.*, !=3.6.*
License-File: LICENSE.rst
License-File: AUTHORS.rst
Dynamic: author
Dynamic: author-email
Dynamic: classifier
Dynamic: description
Dynamic: home-page
Dynamic: license
Dynamic: license-file
Dynamic: platform
Dynamic: requires-python
Dynamic: summary
